django_q_monitor-0.1.0.dist-info/licenses/LICENSE
q_monitor/__init__.py
q_monitor/apps.py
q_monitor/serializers.py
q_monitor/urls.py
q_monitor/views.py
django_q_monitor-0.1.0.dist-info/METADATA
django_q_monitor-0.1.0.dist-info/WHEEL
django_q_monitor-0.1.0.dist-info/top_level.txt
django_q_monitor-0.1.0.dist-info/RECORD
