Metadata-Version: 2.4
Name: django-q-monitor
Version: 0.1.0
Summary: A REST API monitoring tool for Django Q2 queues
Author-email: Alex Previato <245272337+previa1998@users.noreply.github.com>
License: MIT License
Project-URL: Homepage, https://github.com/previa1998/django-q-monitor
Project-URL: Source, https://github.com/previa1998/django-q-monitor
Project-URL: Bug Tracker, https://github.com/previa1998/django-q-monitor/issues
Keywords: django,django-q,monitoring,tasks,queue,api,rest-framework
Classifier: Framework :: Django
Classifier: Framework :: Django :: 4.0
Classifier: Framework :: Django :: 5.0
Classifier: Intended Audience :: Developers
Classifier: License :: OSI Approved :: MIT License
Classifier: Programming Language :: Python :: 3
Classifier: Operating System :: OS Independent
Requires-Python: >=3.9
License-File: LICENSE
Requires-Dist: django>=4.0
Requires-Dist: djangorestframework
Requires-Dist: django-q2
Dynamic: license-file
